{"msg":"","data":{"newsList":[{"commentList":[],"newsId":112,"like":0,"subject":"活动测试","imageUrls":[{"thumbUrl":"/low/18/1433341815300.jpg","origUrl":"/high/18/1433341815300.jpg"}],"type":2,"content":"<p style=\"margin: 0px 3px 15px; padding: 0px; color: rgb(0, 0, 0); font-family: 宋体; font-size: 14px; line-height: 23.7999992370605px; text-indent: 30px;\">中国网6月3日讯（记者 魏方超）以“吹卖嫖赌贪”闻名的湖北天门原市委书记张二江，近日被媒体披露有了新身份：古文献注疏解释专家。据称，在2002年被判处18年有期徒刑的张二江，因积极改造、服刑期间出版4本专著而提前出狱，至今已有5年。<\/p><p style=\"margin: 0px 3px 15px; padding: 0px; color: rgb(0, 0, 0); font-family: 宋体; font-size: 14px; line-height: 23.7999992370605px; text-indent: 30px;\"><\/p><p style=\"margin: 0px 3px 15px; padding: 0px; color: rgb(0, 0, 0); font-family: 宋体; font-size: 14px; line-height: 23.7999992370605px; text-indent: 30px;\">开茶馆，练书法，出版专著，还将开设国学班……张二江出狱后的生活，看起来有声有色。不过，并非每个出狱官员都像张二江这样“与世无争”。记者搜索发现，他们有的还能继续升官，有的甚至收取高额“补偿费”，也有人因各种原因再次获刑。<\/p>","createDate":"2015-06-03","commentCount":0},{"commentList":[],"newsId":74,"like":0,"subject":"","imageUrls":[{"thumbUrl":"/low/18/1432833446726.jpg","origUrl":"/high/18/1432833446726.jpg"}],"type":2,"content":"<p>asdasd<\/p>","createDate":"2015-05-29","commentCount":0},{"commentList":[],"newsId":12,"like":10,"subject":"test4","imageUrls":[{"thumbUrl":"/low/1/1432460250287.jpg","origUrl":"/high/1/1432460250287.jpg"}],"type":2,"content":"test content","createDate":"2015-05-23","commentCount":0},{"commentList":[],"newsId":14,"like":10,"subject":"test6","imageUrls":[],"type":2,"content":"test content","createDate":"2015-05-23","commentCount":0},{"commentList":[],"newsId":25,"like":10,"subject":"test17","imageUrls":[],"type":2,"content":"test content","createDate":"2015-05-23","commentCount":0},{"commentList":[],"newsId":3,"like":10,"subject":"test4","imageUrls":[{"thumbUrl":"/low/1/1432460250312.jpg","origUrl":"/high/1/1432460250312.jpg"},{"thumbUrl":"/low/1/1432464255300.jpg","origUrl":"/high/1/1432464255300.jpg"},{"thumbUrl":"/low/1/1432457741730.jpg","origUrl":"/high/1/1432457741730.jpg"}],"type":2,"content":"test content","createDate":"2015-05-23","commentCount":0},{"commentList":[],"newsId":5,"like":10,"subject":"test6","imageUrls":[{"thumbUrl":"/low/1/1432457741730.jpg","origUrl":"/high/1/1432457741730.jpg"}],"type":2,"content":"test content","createDate":"2015-05-23","commentCount":0}],"businessMsg":"","isLastPage":true,"isSuccess":0},"status":0}