{"msg":"","data":{"businessMsg":"","isLastPage":"true","taskList":[{"studentId":2,"studentName":"张小三","title":"你好","deadline":"2015-06-13","userRole":2,"taskId":15,"completeStatus":0},{"studentId":4,"studentName":"张三","title":"你好","deadline":"2015-06-13","userRole":2,"taskId":15,"completeStatus":0},{"studentId":4,"studentName":"张三","title":"测试反反复复","deadline":"2015-07-13","userRole":2,"taskId":14,"completeStatus":0},{"studentId":8,"studentName":"这样","title":"测试反反复复","deadline":"2015-07-13","userRole":2,"taskId":14,"completeStatus":1},{"studentId":5,"studentName":"zxs","title":"测试反反复复","deadline":"2015-07-13","userRole":2,"taskId":14,"completeStatus":0},{"studentId":9,"studentName":"王小贱","title":"测试反反复复","deadline":"2015-07-13","userRole":2,"taskId":14,"completeStatus":1},{"studentId":3,"studentName":"Jeniss","title":"测试反反复复","deadline":"2015-07-13","userRole":2,"taskId":14,"completeStatus":0},{"studentId":5,"studentName":"zxs","title":"测试反反复复","deadline":"2015-07-13","userRole":2,"taskId":14,"completeStatus":1},{"studentId":2,"studentName":"张小三","title":"测试反反复复","deadline":"2015-07-13","userRole":2,"taskId":14,"completeStatus":0},{"studentId":7,"studentName":"蒋","title":"测试反反复复","deadline":"2015-07-13","userRole":2,"taskId":14,"completeStatus":0},{"studentId":2,"studentName":"张小三","title":"一个过程","deadline":"2015-06-13","userRole":2,"taskId":13,"completeStatus":0},{"studentId":4,"studentName":"张三","title":"一个过程","deadline":"2015-06-13","userRole":2,"taskId":13,"completeStatus":0},{"studentId":2,"studentName":"张小三","title":"骨灰级","deadline":"2015-06-13","userRole":2,"taskId":11,"completeStatus":0},{"studentId":4,"studentName":"张三","title":"MQ_","deadline":"2015-02-01","userRole":2,"taskId":10,"completeStatus":0}],"isSuccess":0},"Status":0}
